ms_utils/__init__.py
ms_utils/_version.py
ms_utils/communication_utils/__init__.py
ms_utils/communication_utils/microservice_ws.py
ms_utils/communication_utils/s3bucket_client.py
ms_utils/encoding_utils/__init__.py
ms_utils/encoding_utils/utils.py
ms_utils/logging_lib/__init__.py
ms_utils/logging_lib/logger.py
ms_utils/logging_lib/utils.py
ms_utils/power_consumption/__init__.py
ms_utils/power_consumption/power_consumption.py
ms_utils/scripts/update_prod_dependencies.py
ms_utils/vdb_utils/README.md
ms_utils/vdb_utils/__init__.py
ms_utils/vdb_utils/_vdb_manager.py
ms_utils/vdb_utils/qdrant_vdb.py
msutils_lib-1.0.2.dist-info/METADATA
msutils_lib-1.0.2.dist-info/WHEEL
msutils_lib-1.0.2.dist-info/entry_points.txt
msutils_lib-1.0.2.dist-info/licenses/LICENSE
msutils_lib-1.0.2.dist-info/RECORD
