Metadata-Version: 2.4
Name: msutils_lib
Version: 1.0.2
Summary: AI Platform Microservice Utils Library
Author: Paul Vandevelde, Mathis Lambert, Yasmin Mzayek, Romain RAPALLINI
License-File: LICENSE
Requires-Python: >=3.10
Requires-Dist: boto3==1.35.99
Requires-Dist: fastembed==0.6.1
Requires-Dist: numpy==2.2.4
Requires-Dist: qdrant-client==1.15.1
Requires-Dist: requests==2.32.3
Requires-Dist: tomlkit==0.13.3
Requires-Dist: websockets==15.0.1
Requires-Dist: zeus-ml==0.10.1
Provides-Extra: dev
Requires-Dist: ipdb; extra == 'dev'
Requires-Dist: ipython; extra == 'dev'
Requires-Dist: ms-utils[style,test]; extra == 'dev'
Provides-Extra: style
Requires-Dist: ruff; extra == 'style'
Provides-Extra: test
Requires-Dist: coverage; extra == 'test'
Requires-Dist: pytest-asyncio; extra == 'test'
Requires-Dist: pytest-cov; extra == 'test'
Requires-Dist: pytest>=7.0.0; extra == 'test'
